docjson.py
setup.py
docjson.egg-info/PKG-INFO
docjson.egg-info/SOURCES.txt
docjson.egg-info/dependency_links.txt
docjson.egg-info/requires.txt
docjson.egg-info/top_level.txt